{
  "scrape_timestamp": "2025-12-28T13:29:28.507369",
  "source_url": "https://kcoj.kycourts.net/ContactList/Search",
  "total_records": 993,
  "output_file": "/Volumes/X10 Pro/Roscoe/scripts/output/ky_court_directory_20251228_132858.csv",
  "columns": [
    "Name",
    "Address",
    "County",
    "Phone_Number",
    "Area",
    "Category"
  ],
  "categories": [
    "Pretrial Services Locations",
    "Drug Court Locations",
    "",
    "District Judges",
    "Circuit Judges",
    "Court of Appeals Judges",
    "Master Commissioners",
    "Circuit Clerks",
    "Court Administrators",
    "Supreme Court Justices",
    "Court Designated Worker Program Locations"
  ],
  "counties": [
    "Anderson",
    "Barren",
    "Boone",
    "Bourbon",
    "Boyd",
    "Boyle",
    "Bracken",
    "Breathitt",
    "Breckinridge",
    "Bullitt",
    "Butler",
    "Calloway",
    "Carter",
    "Christian",
    "Clark",
    "Clay",
    "Crittenden",
    "Davies",
    "Edmonson",
    "Elliot",
    "Fayette",
    "Fleming",
    "Franklin",
    "",
    "Fulton",
    "Gallatin",
    "Grant",
    "Graves",
    "Grayson",
    "Greenup",
    "Hancock",
    "Hardin",
    "Harlan",
    "Hart",
    "Henderson",
    "Henry",
    "Hickman",
    "Hopkins",
    "Jackson",
    "Jefferson",
    "Jessamine",
    "Kenton",
    "Knott",
    "Knox",
    "LaRue",
    "Leslie",
    "Letcher",
    "Lewis",
    "Lincoln",
    "Logan",
    "Madison",
    "Magoffin",
    "Marion",
    "Mason",
    "McCracken",
    "McCreary",
    "Meade",
    "Menifee",
    "Metcalfe",
    "Montgomery",
    "Morgan",
    "Nelson",
    "Ohio",
    "Oldham",
    "Owen",
    "Pendleton",
    "Perry",
    "Pike",
    "Powell",
    "Rowan",
    "Scott",
    "Shelby",
    "Spencer",
    "Trimble",
    "Union",
    "Hart. LaRue & Nelson",
    "Harrison, Nicholas, Pendleton & Robertson",
    "Carroll, Grant & Owen",
    "Clinton, Cumberland",
    "Bracken, Fleming & Mason",
    "Warren",
    "Webster",
    "Whitley",
    "Wolfe",
    "Woodford",
    "Anderson, Bourbon, Boyle, Clark, Fayette, Franklin, Jessamine, Madison, Mercer, Scott, and Woodford",
    "Barren & Metcalfe",
    "Boone & Gallatin",
    "Green, Marion, Taylor & Washington",
    "Clay, Jackson & Leslie",
    "Hart, LaRue & Nelson",
    "McCreary & Whitley",
    "Caldwell",
    "Bath, Menifee, Montgomery & Rowan",
    "Calloway & Marshall",
    "Boyle & Mercer",
    "WHITLEY-CORBIN-118",
    "Carroll",
    "Laurel",
    "Daviess",
    "Bourbon, Scott & Woodford",
    "Marshall",
    "Campbell",
    "Robertson",
    "Butler, Edmonson, Hancock & Ohio",
    "Garrard",
    "Garrard, Jessamine & Lincoln",
    "Webster, Union, Crittendon",
    "McLean",
    "Estill",
    "Todd",
    "Monroe",
    "Anderson, Shelby & Spencer",
    "Carlisle",
    "Owsley",
    "Johnson, Martin & Lawrence",
    "Breckinridge, Grayson & Meade",
    "Casey",
    "Adair, Bell, Casey, Clay, Clinton, Cumberland, Estill, Garrard, Green, Jackson, Knox, Laurel, Lee, Leslie, Lincoln, Marion, McCreary, Metcalfe, Monroe, Nelson, Pulaski, Rockcastle, Russell, Taylor, Washington, Wayne, and Whitley",
    "Allen",
    "Knox & Laurel",
    "Cumberland & Monroe",
    "Mercer",
    "Bath, Boone, Bracken, Campbell, Carroll, Fleming, Gallatin, Grant, Harrison, Henry, Kenton, Lewis, Mason, Nicholas, Oldham, Owen, Pendleton, Robertson, Shelby, Spencer, and Trimble",
    "Johnson",
    "Johnson, Lawrence & Martin",
    "Knott & Magoffin",
    "Lyon",
    "FAYETTE",
    "Clark & Madison",
    "Edmonson & Warren",
    "Boyd, Breathitt, Carter, Elliot, Floyd, Greenup, Harlan, Johnson, Knott, Lawrence, Letcher, Magoffin, Martin, Menifee, Montgomery, Morgan, Owsley, Perry, Pike, Powell, Rowan and Wolfe",
    "Boyd, Breathitt, Carter, Elliott, Floyd, Greenup, Harlan, Johnson, Knott, Lawrence, Letcher, Magoffin, Martin, Menifee, Montgomery, Morgan, Owsley, Perry, Pike, Powell, Rowan and Wolfe",
    "Nicholas",
    "Elliott",
    "Mason, Bracken & Fleming",
    "Edmonson & Hancock",
    "Elliott & Morgan",
    "Jessamin & Garrad",
    "Green, Taylor & Washington",
    "Nelson, Hart & Larue",
    "Logan & Todd",
    "Nelson, Hart & LaRue",
    "Nicholas, Pendleton & Robertson",
    "Henry, Oldham, & Trimble",
    "Taylor",
    "Greenup & Lewis",
    "Oldham, Henry, Trimble",
    "Pendleton & Robertson",
    "Martin",
    "Cumberland",
    "Garrard & Jessamine",
    "Estill, Lee & Owsley",
    "Allen & Simpson",
    "Breathitt, Powell & Wolfe",
    "Green",
    "Barren, Breckinridge, Bullitt, Daviess, Grayson, Hancock, Hardin, Hart, Henderson, Larue, Meade, Ohio, Union, and Warren",
    "Russell & Wayne",
    "Henry & Trimble",
    "Bath",
    "000",
    "Simpson",
    "Pulaski",
    "Rockcastle",
    "Bourbon, Scott, Woodford",
    "Floyd",
    "Pulaski & Rockcastle",
    "Ballard",
    "Crittenden, Webster & Union",
    "Anderson, Shelby, Spencer",
    "Bell",
    "Lee",
    "Wayne",
    "Allen, Ballard, Butler, Caldwell, Calloway, Carlisle, Christian, Crittenden, Edmonson, Fulton, Graves, Hickman, Hopkins, Livingston, Logan, Lyon, Marshall, McCracken, McLean, Muhlenberg, Simpson, Todd, Trigg, and Webster",
    "Washington",
    "Russell",
    "Livingston",
    "Caldwell, Livingston, Lyon and Trigg",
    "Harrison",
    "Ballard, Carlisle, Fulton & Hickman",
    "Clinton, Russell & Wayne",
    "Muhlenberg",
    "Crittenden, Union & Webster",
    "Adair",
    "Adair & Casey",
    "Northern Region",
    "Oldham, Henry & Trimble",
    "Hart & LaRue",
    "Harrison, Nicholas, Pendleton, Robertson",
    "Lincoln, Pulaski & Rockcastle",
    "Garrrard & Jessamine",
    "Carter, Elliott & Morgan",
    "Estill, Lee, Owsley",
    "Clinton",
    "Fulton & Hickman",
    "Lawerence",
    "McLean & Muhlenberg",
    "Trigg",
    "Clinton & Cumberland",
    "Lawrence",
    "Caldwell, Livingston, Lyon & Trigg",
    "Clinton, Cumberland & Monroe"
  ]
}