{
  "duplicates": {
    "J. Chumbley": [
      "@jchumbley",
      "J. Chumbley"
    ],
    "Jessica Whaley": [
      "A G Whaley",
      "A. G. Whaley",
      "AG Whaley",
      "Ag Whaley",
      "Jessica Whaley",
      "Sarena Whaley",
      "Whaley",
      "agwhaley"
    ],
    "Allen Campbell Ewen": [
      "A. Campbell Ewen",
      "Allen Campbell Ewen",
      "Campbell Ewen"
    ],
    "Aaron G. Whaley, Esq.": [
      "Aaron G. Whaley",
      "Aaron G. Whaley, Esq.",
      "Aaron Whaley",
      "Aaron Whaley, Esquire"
    ],
    "Aaron Gregory Whaley, Esq.": [
      "Aaron Gregory Whaley",
      "Aaron Gregory Whaley, Esq."
    ],
    "Aaron W.": [
      "Aaron W.",
      "Aaron Wy"
    ],
    "G. Adam Redden": [
      "Adam Redden",
      "G. Adam Redden"
    ],
    "Aletha N. Thomas, Esq.": [
      "Aletha N Thomas",
      "Aletha N. Thomas",
      "Aletha N. Thomas, Esq.",
      "Aletha Thomas"
    ],
    "Kuebbing, Alexander J.": [
      "Alexander",
      "Alexander J. Kuebbing",
      "Beth Alexander",
      "Kuebbing, Alexander J."
    ],
    "Licha H. Farah, Jr.": [
      "Alicia Farah",
      "Licha H. Farah, Jr."
    ],
    "Allison Wiles (Allie Orberson-Wiles)": [
      "Allie Orberson-Wiles",
      "Allison Orberson-Wiles",
      "Allison Wiles (Allie Orberson-Wiles)"
    ],
    "Allison L. Rief": [
      "Allison L. Rief",
      "Allison L. Riel",
      "Allison Rief"
    ],
    "Bruce Anderson": [
      "Anderson",
      "Bruce Anderson"
    ],
    "Andrea Higgins, Esq.": [
      "Andrea Higgins",
      "Andrea Higgins, Esq.",
      "Andrea L. Higgins"
    ],
    "Aries Paul Penaflor": [
      "Aries Paul Penaflor",
      "Aries Paul Pe\u00f1aflor"
    ],
    "Aries Penaflor": [
      "Aries Penaflor",
      "Aries Pe\u00f1aflor"
    ],
    "Aris L. Rogers": [
      "Aris L. Rogers",
      "Aris Rogers"
    ],
    "Defense Attorney for Forcht Bank": [
      "Attorney",
      "Attorney (drafting)",
      "Attorney Whaley",
      "Defendant's Attorney",
      "Defendants' Attorney",
      "Defense Attorney",
      "Defense Attorney for Forcht Bank",
      "Defense attorney",
      "GDonnell@thattorneys.com",
      "Graser attorney's office",
      "Marshall County probate attorney",
      "Morgan & Morgan attorney",
      "Mr. Graser's attorney's office",
      "Multiple attorneys",
      "Naomi Richardson's attorney",
      "Neltners' attorney",
      "Park Lake Attorney John",
      "Plaintiff's attorney",
      "burch@lbfattorneys.com",
      "defendants' attorney",
      "defense attorney",
      "former attorney",
      "previous attorney",
      "vherbert@thattorneys.com"
    ],
    "BEN Rettig": [
      "BEN Rettig",
      "Ben Rettig"
    ],
    "BRANN, CHRISTOPHER THOMAS": [
      "BRANN, CHRISTOPHER THOMAS",
      "Brann, Christopher Thomas"
    ],
    "Bethany WIllcutt": [
      "Bethany WIllcutt",
      "Bethany Wilcutt",
      "Bethany Willcutt"
    ],
    "Betsy R. Catron": [
      "Betsy Catron",
      "Betsy R Catron",
      "Betsy R. Catron"
    ],
    "Blake A. Gerstner": [
      "Blake A. Gerstner",
      "Blake Gerstner"
    ],
    "Blake V. Edwards": [
      "Blake Edwards",
      "Blake V. Edwards"
    ],
    "Bobby L. Whitmer": [
      "Bobby L. Whitmer",
      "Bobby Whitmer"
    ],
    "Brian D. Stempien": [
      "Brian D. Stempien",
      "Brian Stempien",
      "Stempien"
    ],
    "Sarena (Whaley Law Firm)": [
      "Bryce (Whaley Law Firm)",
      "Sarena (Whaley Law Firm)"
    ],
    "Bryce L. Cotton": [
      "Bryce Cotton",
      "Bryce L. Cotton"
    ],
    "Bryce W. Koon, Esq.": [
      "Bryce Koon",
      "Bryce Koon, Esq.",
      "Bryce Koons",
      "Bryce W. Koon",
      "Bryce W. Koon, Esq.",
      "W. Bryce Koon",
      "W. Bryce Koon, Esq."
    ],
    "Charles Walker, Esq.": [
      "Charles A. Walker",
      "Charles Walker",
      "Charles Walker, Esq.",
      "Charlie A. Walker",
      "Charlie Walker"
    ],
    "Chauncey R. Hiestand": [
      "Chauncey Heistand",
      "Chauncey Hiestand",
      "Chauncey R. Hiestand",
      "Heistand"
    ],
    "Christopher M. Mussler": [
      "Christopher M Mussler",
      "Christopher M. Mussler"
    ],
    "Clay E. Thornton": [
      "Clay E. Thornton",
      "Thornton"
    ],
    "Defense Counsel for Mr. Turner": [
      "Counsel",
      "DC (defense counsel)",
      "Defense Counsel",
      "Defense Counsel (DC)",
      "Defense Counsel for Mr. Turner",
      "Defense counsel",
      "Defense counsel (DC)",
      "Mr. Turner's Counsel",
      "Opposing counsel",
      "Plaintiff counsel",
      "Plaintiff's counsel",
      "defense counsel",
      "defense counsel for Travelers"
    ],
    "David T. Klapheke": [
      "David Klapheke",
      "David T Klapheke",
      "David T. Klapheke"
    ],
    "Deanna M. Marzian Tucker": [
      "Deanna M. Marzian Tucker",
      "Deanna Marie Tucker"
    ],
    "Deanna M. Tucker, Esq.": [
      "Deanna M. Tucker",
      "Deanna M. Tucker, Esq.",
      "Deanna Tucker"
    ],
    "Debora(h) Dilbeck": [
      "Debora(h) Dilbeck",
      "Deborah Dilbeck"
    ],
    "Deborah Campbell Myers": [
      "Deborah",
      "Deborah C. Myers",
      "Deborah Campbell Myers",
      "Deborah Dilbeck Myers",
      "Deborah Jackson",
      "Deborah Myers"
    ],
    "Doug (dusellis@umakylaw.com)": [
      "Doug (dusellis@umakylaw.com)",
      "Dusellis"
    ],
    "Doug Dusellis": [
      "Doug Dusellis",
      "Doug U'Sellis",
      "Doug U\u2019Sellis"
    ],
    "Douglas A. U'Sellis": [
      "Douglas A. U'Sellis",
      "Douglas U'Sellis",
      "Douglas U\u2019Sellis"
    ],
    "Eddie A. Jones": [
      "Eddie A. Jones",
      "Eddie Jones"
    ],
    "Eric S. Rice, Esq.": [
      "Eric Rice",
      "Eric S. Rice",
      "Eric S. Rice, Esq."
    ],
    "George B. Hocker": [
      "George B. Hocker",
      "Hocker"
    ],
    "Gregory Gowen": [
      "Greg Gowen",
      "Gregory Gowen"
    ],
    "Greg Thornton": [
      "Greg Thorn",
      "Greg Thornton"
    ],
    "Gregg E. Thornton": [
      "Gregg E. Thornton",
      "Gregg Thornton"
    ],
    "Gregory Scott Gowen": [
      "Gregory Scott Gowen",
      "Scott Gowen",
      "Scott Gowen, Esq."
    ],
    "HOLLAN, JONATHAN": [
      "HOLLAN, JONATHAN",
      "Hollan, Jonathan"
    ],
    "Hiestand, Chauncey R.": [
      "Hiestand",
      "Hiestand, Chauncey R."
    ],
    "Hon. Thomas J. Knopf": [
      "Hon. Thomas J. Knopf",
      "Hon. Thomas Knopf",
      "Thomas Knopf"
    ],
    "James Kamensky, Esq.": [
      "James Kamensky",
      "James Kamensky, Esq."
    ],
    "James R. Coltharp Jr.": [
      "James R. Coltharp",
      "James R. Coltharp Jr."
    ],
    "John J. Ellis, Esq.": [
      "Jason Ellis",
      "John Ellis",
      "John J. Ellis",
      "John J. Ellis, Esq."
    ],
    "Jeff Roberts": [
      "Jeff Roberts",
      "Robert"
    ],
    "Jeremy Winton": [
      "Jeremy Winton",
      "Winton"
    ],
    "Jessica (Whaley Law Firm)": [
      "Jessica",
      "Jessica (Whaley Law Firm)",
      "Jessica Bottorff",
      "Jessica Poalini",
      "Jessica Wiedersatz",
      "jessica@whaleylawfirm.com"
    ],
    "Jillian D. House": [
      "Jillian D. House",
      "Jillian House"
    ],
    "Jody B. Gabel": [
      "Jody B. Gabel",
      "Jody Gable"
    ],
    "John D. Bertram, Esq.": [
      "John Bertram",
      "John D. Bertram",
      "John D. Bertram, Esq."
    ],
    "John F. Parker, Jr.": [
      "John F. Parker, Jr.",
      "John Parker"
    ],
    "John Strom": [
      "John Strom",
      "Jon Strom"
    ],
    "Joseph M. Effinger, Esq.": [
      "Joseph Effinger",
      "Joseph Effinger, Esq.",
      "Joseph M. Effinger",
      "Joseph M. Effinger, Esq."
    ],
    "Josh Leckrone, Esq.": [
      "Josh Leckrone",
      "Josh Leckrone, Esq.",
      "Joshua J. Leckrone",
      "Joshua Leckrone"
    ],
    "Justin (Whaley Law Firm)": [
      "Justin",
      "Justin (Whaley Law Firm)",
      "Justin (Whaley law firm)",
      "Justin Chumbley",
      "Justin Whaley"
    ],
    "Kaylee F. Collins": [
      "Kaley Collins",
      "Kaylee Collins",
      "Kaylee F. Collins"
    ],
    "Katie Nelson Dunn": [
      "Katie Nelson",
      "Katie Nelson Dunn"
    ],
    "Katie Watts, Esq.": [
      "Katie Watts",
      "Katie Watts, Esq."
    ],
    "Lance Lucas, Esq.": [
      "Lance Lucas",
      "Lance Lucas, Esq."
    ],
    "Lee E. Sitlinger": [
      "Lee E. Sitlinger",
      "Lee Sitlinger",
      "Leroy Sitlinger"
    ],
    "Mary S. Johnson": [
      "Mary Johnson",
      "Mary S. Johnson"
    ],
    "Matthew R. Londergan": [
      "Matt Londergan",
      "Matt Lonergan",
      "Matthew Londergan",
      "Matthew R Londergan",
      "Matthew R. Londergan"
    ],
    "Matthew A. Piekarski": [
      "Matthew A. Piekarski",
      "Matthew Piekarski"
    ],
    "Matthew B. Steinberg, Esq.": [
      "Matthew B. Steinberg",
      "Matthew B. Steinberg, Esq.",
      "Matthew Steinberg"
    ],
    "Max D. Smith": [
      "Max D. Smith",
      "Max Smith"
    ],
    "Maxwell D. Smith, Esq.": [
      "Maxwell D. Smith",
      "Maxwell D. Smith, Esq.",
      "Maxwell Smith"
    ],
    "Mr. Nafziger (rnafziger@ppoalaw.com)": [
      "Mr. Nafziger",
      "Mr. Nafziger (rnafziger@ppoalaw.com)"
    ],
    "Nichole M. Priddy, Esq.": [
      "Nichole M. Priddy",
      "Nichole M. Priddy, Esq."
    ],
    "Paige E. Hornback": [
      "Paige E. Hornback",
      "Paige Hornback"
    ],
    "Patrick A. Ross": [
      "Patrick A. Ross",
      "Patrick Ross"
    ],
    "Richard E. Neal (Rick Neal)": [
      "Richard E. Neal",
      "Richard E. Neal (Rick Neal)"
    ],
    "Rick Neal, Esq.": [
      "Rick Neal",
      "Rick Neal, Esq."
    ],
    "Robert Lee Sneed III": [
      "Robert Lee Sneed III",
      "Robert Sneed"
    ],
    "Ryan D. Nafziger, Esq.": [
      "Ryan D. Nafziger",
      "Ryan D. Nafziger, Esq.",
      "Ryan Nafziger",
      "Ryan Nafziger, Esq."
    ],
    "Ryan J. McElroy": [
      "Ryan J. McElroy",
      "Ryan McElroy"
    ],
    "sgowen@fmdlegal.com (S. Gowen)": [
      "S. Gowen",
      "sgowen@fmdlegal.com (S. Gowen)"
    ],
    "Sarena M. Tuttle": [
      "Saraena Tuttle",
      "Sarena M. Tuttle",
      "Sarena Tuttle",
      "Serena Tuttle"
    ],
    "Sarena (Whaley Law Firm email recipient)": [
      "Sarena",
      "Sarena (Sarena@whaleylawfirm.com)",
      "Sarena (The Whaley Law Firm)",
      "Sarena (Whaley Law Firm email recipient)",
      "Sarena@whaleylawfirm.com"
    ],
    "Scott Stoutheukelaw": [
      "Scott Stout",
      "Scott Stoutheukelaw"
    ],
    "Steven B. Lowery, Esq.": [
      "Steven B. Lowery",
      "Steven B. Lowery, Esq.",
      "Steven Lowery",
      "Steven Lowery, Esq."
    ],
    "Steven P. Stadler": [
      "Steven P. Stadler",
      "Steven Stadler"
    ],
    "Taylor L. Kellebrew": [
      "Taylor Kellebrew",
      "Taylor L. Kellebrew"
    ],
    "Taylor L. Marak": [
      "Taylor L. Marak",
      "Taylor Marak"
    ],
    "Thomas Blankenship": [
      "Thomas Blankenship",
      "Tom Blankenship"
    ],
    "Valerie Herbert, Esq.": [
      "Valerie Anne Herbert",
      "Valerie Herbert",
      "Valerie Herbert, Esq.",
      "Valerie W. Herbert"
    ],
    "WHALEY, AARON GREGORY": [
      "WHALEY, AARON GREGORY",
      "Whaley, Aaron Gregory"
    ],
    "William B. Orber-son": [
      "William B. Orber-son",
      "William B. Orbereson",
      "William B. Orberson",
      "William B. Orbeson",
      "William Orberson"
    ],
    "William J. Barker, II": [
      "William J. Barker II",
      "William J. Barker, II"
    ],
    "Zachary Reichle, Esq.": [
      "Zach Reichle",
      "Zachary Reichle",
      "Zachary Reichle, Esq."
    ],
    "davidsonb@obtlaw.com": [
      "davidsonb@obtlaw.com",
      "davisj@obtlaw.com"
    ]
  },
  "staff_misclassified": {
    "Sarena M. Tuttle": {
      "correct_name": "Sarena Tuttle",
      "correct_type": "CaseManager",
      "role": "paralegal"
    },
    "Sarena Tuttle": {
      "correct_name": "Sarena Tuttle",
      "correct_type": "CaseManager",
      "role": "paralegal"
    },
    "Bryce Koon": {
      "correct_name": "Bryce Koon",
      "correct_type": "Attorney",
      "role": "attorney"
    },
    "W. Bryce Koon": {
      "correct_name": "Bryce Koon",
      "correct_type": "Attorney",
      "role": "attorney"
    },
    "Jessa Galosmo": {
      "correct_name": "Jessa Galosmo",
      "correct_type": "CaseManager",
      "role": "case_manager"
    },
    "Aaron Gregory Whaley": {
      "correct_name": "Aaron Gregory Whaley",
      "correct_type": "Attorney",
      "role": "attorney"
    },
    "Aaron Whaley": {
      "correct_name": "Aaron G. Whaley",
      "correct_type": "Attorney",
      "role": "attorney"
    },
    "Justin Chumbley": {
      "correct_name": "Justin Chumbley",
      "correct_type": "CaseManager",
      "role": "case_manager"
    },
    "Jessica Bottorff": {
      "correct_name": "Jessica Bottorff",
      "correct_type": "CaseManager",
      "role": "case_manager"
    },
    "Aries Penaflor": {
      "correct_name": "Aries Penaflor",
      "correct_type": "CaseManager",
      "role": "case_manager"
    },
    "Aaron Gregory Whaley, Esq.": {
      "correct_name": "Aaron Gregory Whaley",
      "correct_type": "Attorney",
      "role": "attorney"
    },
    "Faye Gaither": {
      "correct_name": "Faye Gaither",
      "correct_type": "CaseManager",
      "role": "case_manager"
    },
    "Aaron G. Whaley": {
      "correct_name": "Aaron G. Whaley",
      "correct_type": "Attorney",
      "role": "attorney"
    },
    "Bryce W. Koon": {
      "correct_name": "Bryce Koon",
      "correct_type": "Attorney",
      "role": "attorney"
    },
    "Jessa": {
      "correct_name": "Jessa",
      "correct_type": "CaseManager",
      "role": "case_manager"
    },
    "Serena Tuttle": {
      "correct_name": "Sarena Tuttle",
      "correct_type": "CaseManager",
      "role": "paralegal"
    },
    "Aries Pe\u00f1aflor": {
      "correct_name": "Aries Penaflor",
      "correct_type": "CaseManager",
      "role": "case_manager"
    },
    "Saraena Tuttle": {
      "correct_name": "Sarena Tuttle",
      "correct_type": "CaseManager",
      "role": "paralegal"
    },
    "Bryce Koons": {
      "correct_name": "Bryce Koon",
      "correct_type": "Attorney",
      "role": "attorney"
    }
  },
  "stats": {
    "total_unique_mentions": 591,
    "duplicate_sets": 101,
    "staff_misclassified": 19,
    "total_corrections": 120
  }
}