[
  {
    "jsonb_agg": [
      {
        "email": "jaekale2005@gmail.com",
        "phone": "502-755-1288",
        "roles": [
          "client"
        ],
        "address": "607 Alger Ave,  ",
        "full_name": "Jae-Kale Lewis",
        "contact_id": 2090,
        "project_name": "Jae-Kale-Lewis-MVA-02-24-2025"
      },
      {
        "email": null,
        "phone": null,
        "roles": [
          "payee"
        ],
        "address": "2951 Marina Bay Drive, Suite 130-132, League City, TX 77573",
        "full_name": "ChartSwap",
        "contact_id": 421,
        "project_name": "Jae-Kale-Lewis-MVA-02-24-2025"
      },
      {
        "email": "statefarmclaims@statefarm.com",
        "phone": "844-292-8615 xt 506 Main",
        "roles": [
          "adjuster"
        ],
        "address": null,
        "full_name": "State Farm PIP Team",
        "contact_id": 964,
        "project_name": "Jae-Kale-Lewis-MVA-02-24-2025"
      },
      {
        "email": "statefarmclaims@statefarm.com",
        "phone": "678-935-3274",
        "roles": [
          "adjuster"
        ],
        "address": null,
        "full_name": "Steve Campbell",
        "contact_id": 1204,
        "project_name": "Jae-Kale-Lewis-MVA-02-24-2025"
      },
      {
        "email": "statefarmclaims@statefarm.com",
        "phone": "1-800-782-8332",
        "roles": [
          "insurance_company"
        ],
        "address": "P.O Box 106171, Atlanta, GA 30348",
        "full_name": "State Farm Insurance Company",
        "contact_id": 220,
        "project_name": "Jae-Kale-Lewis-MVA-02-24-2025"
      },
      {
        "email": "subrogationreferrals@optum.com",
        "phone": "888-870-8842",
        "roles": [
          "lien_holder"
        ],
        "address": "P.O. Box 5270, Kingston, NY 12402",
        "full_name": "United Healthcare",
        "contact_id": 239,
        "project_name": "Jae-Kale-Lewis-MVA-02-24-2025"
      },
      {
        "email": null,
        "phone": "877-842-3210",
        "roles": [
          "lien_holder"
        ],
        "address": "P.O Box 31362, Salt Lake City, UT 84131",
        "full_name": "United Healthcare",
        "contact_id": 1020,
        "project_name": "Jae-Kale-Lewis-MVA-02-24-2025"
      },
      {
        "email": "starliteinjurycare963@outlook.com",
        "phone": "502-991-2056",
        "roles": [
          "medical_provider"
        ],
        "address": "1169 Eastern Pkwy, , Louisville, KY 40217",
        "full_name": "Starlite Chiropractic",
        "contact_id": 219,
        "project_name": "Jae-Kale-Lewis-MVA-02-24-2025"
      },
      {
        "email": null,
        "phone": null,
        "roles": [
          "medical_provider"
        ],
        "address": "3231 North Star Circle, Louisville, TN 37777",
        "full_name": "Southeastern Emergency Services, LLC",
        "contact_id": 932,
        "project_name": "Jae-Kale-Lewis-MVA-02-24-2025"
      },
      {
        "email": "ulhcustomerservice@uoflhealth.org",
        "phone": "(502) 587-4925 Main",
        "roles": [
          "medical_provider"
        ],
        "address": "1850 Bluegrass Ave, , Louisville, KY 40215",
        "full_name": "UofL Health - Mary & Elizabeth Mary & Elizabeth Hospital",
        "contact_id": 1499,
        "project_name": "Jae-Kale-Lewis-MVA-02-24-2025"
      }
    ]
  }
]